src/thread_last/__init__.py
src/thread_last/lib.py
thread_last-0.1.0.dist-info/LICENSE
thread_last-0.1.0.dist-info/METADATA
thread_last-0.1.0.dist-info/WHEEL
thread_last-0.1.0.dist-info/RECORD
