Metadata-Version: 2.1
Name: thread-last
Version: 0.1.0
Summary: thread-last for Python
License: Apache-2.0
Author: Naoya Yamashita
Author-email: conao3@gmail.com
Requires-Python: >=3.12,<4.0
Classifier: License :: OSI Approved :: Apache Software License
Classifier: Programming Language :: Python :: 3
